test_poetry99/__init__.py
test_poetry99/auth.py
test_poetry99/blog.py
test_poetry99/db.py
test_poetry99/schema.sql
test_poetry99/static/style.css
test_poetry99/templates/auth/login.html
test_poetry99/templates/auth/register.html
test_poetry99/templates/base.html
test_poetry99/templates/blog/create.html
test_poetry99/templates/blog/index.html
test_poetry99/templates/blog/update.html
test_poetry99-0.2.0.dist-info/WHEEL
test_poetry99-0.2.0.dist-info/METADATA
test_poetry99-0.2.0.dist-info/RECORD
